{
  "color": [
    {
      "name": "start_window_background",
      "value": "#FFFFFF"
    },
    {
      "name": "primary",
      "value": "#0076f6"
    },
    {
      "name": "second_primary",
      "value": "#c0dcf3"
    },
    {
      "name": "backGroundColor_second",
      "value": "#3d97f8"
    },
    {
      "name": "text_primary",
      "value": "#2A2929"
    },
    {
      "name": "text_second",
      "value": "#818181"
    },
    {
      "name": "back_color",
      "value": "#ededed"
    },
    {
      "name": "second_back_color",
      "value": "#f3f4f5"
    },
    {
      "name": "border_color",
      "value": "#f4f5f6"
    },
    {
      "name": "danger",
      "value": "#e75f58"
    },
    {
      "name": "white",
      "value": "#ffffff"
    },
    {
      "name": "bottom_color",
      "value": "#a4a4a4"
    },
    {
      "name": "bottom_voice_color",
      "value": "#515151"
    },
    {
      "name": "voice_back_color",
      "value": "#CC3E3E3E"
    },
    {
      "name": "voice_round_color",
      "value": "#323232"
    },
    {
      "name": "voice_round_font_color",
      "value": "#919191"
    },
    {
      "name": "ding_primary",
      "value": "#c0dcf3"
    },
    {
      "name": "animate_voice_color",
      "value": "#0076f6"
    },
    {
      "name": "black",
      "value": "#000000"
    },
    {
      "name": "popup_back",
      "value": "#4d4d4d"
    },
    {
      "name": "text_gray",
      "value": "#ddd"
    }
  ]
}